{
    "EndPoint": "ykv8z5",
    "Data": {
        "clients": 0,
        "gametype": "RolePlay",
        "hostname": "^6[GERMAN]  ^4E^6N^4D^6L^4E^6S^4S  ^6R^4o^6l^4e^6p^4l^6a^4y  | ✅  ^2Keine-Whitelist | 👮 ^4Cops & ^1👩‍⚕️ Medics gesucht! | 💣 ^1AntiCheat  | 🔊 ^4SaltyChat | 🎉 ^4Events | 💊 ^1Illegale/Legale Routen | 🚗 ^4Modded Cars | 🔥 ^6Performance",
        "mapname": "Endless | Map",
        "sv_maxclients": 128,
        "enhancedHostSupport": true,
        "resources": [
            "hardcap",
            "ghispo2",
            "code3megapackrb",
            "polmp4",
            "c8cop",
            "dogeems",
            "gouvcar",
            "polo_gouvernementjob",
            "esx_duty",
            "esx_fibjob",
            "yarn",
            "Cinema",
            "endless_grenzen",
            "mcdonalds",
            "autoschool",
            "verpi_jobcentre",
            "CourtHouse",
            "mess_lsc",
            "mosleynutt",
            "cityhallv2",
            "AutoLuxe",
            "sportracer",
            "ikea",
            "marabunta",
            "dwmansion",
            "mansion",
            "bloodsv2",
            "mess_elk_lob",
            "agerars",
            "esx_gouvernmentGarage",
            "gokart",
            "truck",
            "esx_policejob",
            "corvette",
            "pagani",
            "gt86",
            "gtaelitcm",
            "passat",
            "mk1rabbit",
            "twingo",
            "dyc3a6",
            "r820",
            "_q820",
            "audiq7",
            "rmodrs6",
            "rs7",
            "rmodcharger69",
            ".720s",
            "terzo",
            "matus_sanders",
            "lp700",
            "project8",
            "rmodmartin",
            "bmwm8",
            "Redwood",
            "bmwe38",
            ".m3e30",
            ".mansm8",
            "rmodbacalar",
            "teslamodels",
            "KTMRC39019",
            "s8d2",
            "ktmsm",
            "foxshelby",
            "RAPTOR150",
            "MercedesGT63sAMG",
            "_amggtsprior",
            "s63w222",
            "e63amg",
            "s600w220",
            "s500w222",
            "m3e36",
            "600sl",
            "scooter",
            "CLS63S",
            "glemb",
            "skyline",
            "Nismo20GTR",
            "mlnovitec",
            "Porsche911TurboS",
            "smg",
            "limo",
            "911rwb",
            "18performante",
            "esx_carwash",
            "tabac",
            "mqgts",
            "esx_contract",
            "cg160",
            "esx_townhall",
            "esx_mechanicjob",
            "esx_advancedholdup",
            "en_healing",
            "en_hud",
            "AGM_GYM",
            "_cfx_internal",
            "en_dienstausweislspd",
            "FiveM-BanSql",
            "eup-stream",
            "d-phone",
            "WasGehtSieDasAn",
            "d99",
            "Hollister%20Long%20Sleeve%20Pack",
            "esx_vehiclesRent",
            "esx_tattooshop",
            "corcovado",
            "EnhancedBarber",
            "bobo_prison",
            "esx_optionalneeds",
            "krz_personalmenu",
            "en_notify",
            "gallardo",
            "esx_doorlock",
            "en_progress",
            "fivem-map-hipster",
            "rmodmk7",
            "hose",
            "newpark",
            "esx_marker",
            "lspd_map",
            "esx_cichysim",
            "Phillbox2",
            "nui_doorlock",
            "kurantbar",
            "savewheelpos",
            "en_aduty",
            "rmodf40",
            "patoche_fight",
            "lafa2k_modernhouse",
            "webpack",
            "scripto_tankstelle",
            "_2015a3",
            "en_banking",
            "taxi",
            "Endless",
            "hookah_almeida",
            "fivem",
            "burger",
            "en_vehiclemenu",
            "bobo_prison_lobby",
            "aperta",
            "monitor",
            "Fluffy%20Hair%20Female",
            "en_announce_restart",
            "chat",
            "voicemute",
            "ELS-FiveM",
            "en_eisenerz",
            "en_baumarkt",
            "esx_bitcoin",
            "urus",
            "esx_billing",
            "CarryPeople",
            "en_trauben",
            "en_orangen",
            "Double%20bun%20hairstyle",
            "screenshot-basic",
            "en_kroeten",
            "Male%20Dodgers%20Jersey",
            "hookahv2_almeiidaa",
            "pointFinger",
            "mustang68",
            "en_weed",
            "esx_ambulancejob",
            "simpletp",
            "EngineToggle",
            "async",
            "en_supermarkt",
            "setroannounce",
            "golfgti",
            "MafiaMap",
            "esx_plasticsurgery",
            "simplesync",
            "en_carmenu",
            "kleid1",
            "pub",
            "patoche_cyberbar_map",
            "en_pausemenu",
            "MercedesG65AMG",
            "NativeUILua_Reloaded",
            "el_bwh",
            "salty_craftingzivi",
            "polgs350",
            "NativeUI",
            "essentialmode",
            "gsxr",
            "bob74_ipl",
            "invader",
            "vanilla-ext",
            "Shelby_PonytailHair",
            "saltychat",
            "bens_cuff_item",
            "ponytailhairstyle",
            "wraith",
            "qashqai16",
            "gif_logo",
            "nonpc",
            "stamina",
            "fivem-ipl",
            "ParkingV",
            "btw_tankstelle",
            "esx_givevehicle",
            "en_impound",
            "salty_crafting",
            "5",
            "es_ui",
            "esx_lscustom",
            "wgc_ui",
            "en_visum",
            "esx_vehicleshop",
            "Apron",
            "bennys_Benny",
            "timertazer",
            "PoliceVehiclesWeaponDeleter",
            "en_system",
            "playboy_v2",
            "airport",
            "dpemotes",
            "myMultichar",
            "MercedesGT63Police",
            "deadcam",
            "esx_license",
            "qalle_coords",
            "PvP",
            "G-dragon",
            "8",
            ".mclaren2",
            "en_npc",
            "JF_SeatShuffle",
            "en_restart",
            "esx_vangelico_robbery",
            "jsfour-licenseplate",
            "almeiidaa_hookah_script",
            "Louis%20Vuitton%20Bag%20Female",
            "cloth_menu",
            "2",
            "Rasen",
            "en_uniformen",
            "discordroles",
            "endless_Liberty",
            "en_inventory",
            "esx_datastore",
            "en_announce",
            ".acs8",
            "7",
            "save-position",
            "skinchanger",
            "Caps",
            "mp_map",
            "Chain%20Top%20Female",
            "ems1",
            "en_waffenschaden",
            "polamggtr",
            "spawnmanager",
            "3",
            "Nike%20OFF%20WHite%20T-Shirt",
            "MeetingPointV",
            "_2015s3",
            "SaltyNUI",
            "NewWeddingDress",
            "en_waffenshop",
            "es_admin2",
            "esx_carthief",
            "en_frakinvite",
            "interiors",
            "en_cars",
            "m4LB",
            "frs",
            "mapmanager",
            "ig_tracydisanto",
            "pol718",
            "m3gtr",
            "en_loading",
            "jsfour-idcard",
            "champion_pants",
            "mess_elk_bar",
            "esx-qalle-jail",
            "GangMask",
            "Nike%20Cap",
            "NikeHoodieFivem",
            "gabz_vu",
            "cardealership",
            "esx_holdup",
            "esx_blackmoney",
            "Yeezy",
            "backpacks",
            "eup-ui",
            "mvisiongt",
            "sessionmanager",
            "GucciTshirt",
            "rmodx6",
            "chapion_hoodie",
            "en_notifications",
            "esx_armour_db",
            "PonyTail%20hairstyle",
            "myClothesAPI",
            "es_extended",
            "esx_rpchat",
            "mysql-async",
            "esplugin_mysql",
            "esx_carlock",
            "myATMRobbery",
            "serverlogging",
            "DiscordWhitelist",
            "iFruit",
            "richpresence",
            "progbars",
            "pacific_bank",
            "myDrugs",
            "instance",
            "cron",
            "brigada",
            "esx_lowrider",
            "en_garage",
            "rconlog",
            "traindiner",
            "EasyAdmin",
            "myProperties",
            ".sandcatmx",
            "myClothesshop",
            "l247themorgansuccess",
            "int_weed",
            ".mgt",
            "myRobbery",
            "myRealestateagent",
            "BMCI",
            "Cadillac",
            "myCharCreator",
            "9",
            "esx_carinventory",
            "esx_teleportpads",
            "4",
            "esx_truckshop",
            "esx_addoninventory",
            "1",
            "esx_yakuzajob",
            "gl63",
            "esx_kingsmanjob",
            "Belted%20jeans",
            "esx_camorra",
            "esx_lcnjob",
            "esx_menu_list",
            "BeanMachine",
            "High%20Socks%20Female",
            "esx_menu_default",
            "esx_menu_dialog",
            "esx_holdupbank",
            "amggtr",
            "esx_motorcycles",
            "en_antiwaffenschlag",
            "esx_trunk",
            "m5f90",
            "meta_libs",
            "esx_boatshop",
            "en_plateshop",
            "esx_dmvschool",
            "esx_playtime",
            "esx_addonaccount",
            "en_handyshop",
            "esx_jb_migrate",
            "chiron",
            "esx_blackmarket",
            "bennys_Elevator",
            "lafa2k_finalfantasyxv",
            "esx_society",
            "sound",
            "Knot%20Cropped%20Top%20Female",
            "esx_extraitems",
            "esx_status",
            "esx_basicneeds",
            "esx_accessoriest",
            "vineyards",
            "esx_playermenu",
            "esx_skin"
        ],
        "server": "FXServer-master v1.0.0.3957 linux",
        "vars": {
            "EssentialModeUUID": "65233621-042f-42b0-a3fd-3a3a04194244",
            "EssentialModeVersion": "6.4.2",
            "Routen": "🌿Gras,💊Meth,🍊Orangen,🍇Trauben,🗿Steine,▫️Eisenerz,🐸Kröten,▫️Bauxit",
            "banner_connecting": "https://cdn.discordapp.com/attachments/821492910474133578/831188497040932884/endless_banner.png",
            "banner_detail": "https://i.ibb.co/wgPG3pp/fivembanner.gif%22",
            "gamename": "gta5",
            "locale": "de-DE",
            "onesync_enabled": "true",
            "sv_enforceGameBuild": "2189",
            "sv_enhancedHostSupport": "true",
            "sv_lan": "false",
            "sv_licenseKeyToken": "1662713xkkberry8dl9zes5f_2213249:526402c0c640ef71aab22d0e53fcc1053b0de75f096889d504ea7da1fd635ac4",
            "sv_maxClients": "128",
            "sv_projectDesc": "Einzigartiger Server | TS: endlessroleplay | Discord: dc.endlessroleplay.de",
            "sv_projectName": "🌟 ^4E^6N^4D^6L^4E^6S^4S 🌟 ^2Roleplay",
            "sv_scriptHookAllowed": "false",
            "tags": "roleplay, endless, german, German, GERMAN, onesync, rp, esx, custom scripts, saltychat,esx",
            "txAdmin-version": "3.8.0",
            "📝 Discord": "dc.endlessroleplay.de",
            "🔊 Teamspeak": "endlessroleplay",
            "🔥 Roleplay ": "German",
            "premium": "au"
        },
        "selfReportedClients": 0,
        "players": [],
        "ownerID": 2213249,
        "connectEndPoints": [
            "45.142.114.32:30120"
        ],
        "upvotePower": 7,
        "support_status": "supported",
        "svMaxclients": 128,
        "ownerName": "EndlessRolePlayDE",
        "ownerProfile": "https://forum.cfx.re/u/EndlessRolePlayDE",
        "ownerAvatar": "https://avatars.discourse.org/v4/letter/e/7933a0/128.png",
        "lastSeen": "2021-05-29T04:19:59.1179938Z",
        "iconVersion": 752999470
    }
}